mcp_ry_server/__init__.py
mcp_ry_server/mcp.py
mcp_ry_server-0.1.0.dist-info/METADATA
mcp_ry_server-0.1.0.dist-info/WHEEL
mcp_ry_server-0.1.0.dist-info/entry_points.txt
mcp_ry_server-0.1.0.dist-info/RECORD
