Metadata-Version: 2.4
Name: mcp-ry-server
Version: 0.1.0
Summary: Add your description here
Author: ry
Requires-Python: >=3.10
Requires-Dist: mcp[cli]>=1.7.1
